gumsh_py/__init__.py
gumsh_py/gumsh_py.py
gumsh_py-1.1.1.dist-info/METADATA
gumsh_py-1.1.1.dist-info/WHEEL
gumsh_py-1.1.1.dist-info/licenses/LICENSE
gumsh_py-1.1.1.dist-info/RECORD
