Metadata-Version: 2.3
Name: gumsh_py
Version: 1.1.1
Summary: gumsh_py is a Python interface of charm.sh's shell tool called gum
Project-URL: Homepage, https://github.com/alexjhewitt/gumsh-py
Project-URL: Issues, https://github.com/alexjhewitt/gumsh-py/issues
Author-email: Alex Hewitt <alexhewitt.j@gmail.com>
Classifier: License :: OSI Approved :: MIT License
Classifier: Operating System :: OS Independent
Classifier: Programming Language :: Python :: 3
Requires-Python: >=3.8
